{
    "status": "0000", 
    "data": {
        "24H_fluctate": "-278000", 
        "24H_fluctate_rate": "-2.87", 
        "average_price": "9506154.6936", 
        "opening_price": "9677000", 
        "units_traded": "3384.70974514", 
        "buy_price": "9399000", 
        "sell_price": "9400000", 
        "min_price": "9285000", 
        "volume_7day": "32757.50205662", 
        "date": "1560135631691", 
        "closing_price": "9399000", 
        "volume_1day": "3384.70974514", 
        "max_price": "9727000"
    }
}