{
    "status": "0000", 
    "data": {
        "24H_fluctate": "112000", 
        "24H_fluctate_rate": "1.18", 
        "average_price": "9632390.4087", 
        "opening_price": "9460000", 
        "units_traded": "3799.79848921", 
        "buy_price": "9572000", 
        "sell_price": "9579000", 
        "min_price": "9398000", 
        "volume_7day": "28997.78734686", 
        "date": "1560237155406", 
        "closing_price": "9572000", 
        "volume_1day": "3799.79848921", 
        "max_price": "9788000"
    }
}